flux0_core/__init__.py
flux0_core/agents.py
flux0_core/async_utils.py
flux0_core/background_tasks_service.py
flux0_core/contextual_correlator.py
flux0_core/ids.py
flux0_core/logging.py
flux0_core/py.typed
flux0_core/sessions.py
flux0_core/types.py
flux0_core/users.py
flux0_core/agent_runners/api.py
flux0_core/agent_runners/context.py
flux0_core/agent_runners/helpers.pyTODO
flux0_core/storage/nanodb_memory.py
flux0_core/storage/types.py
flux0_core-0.1.0b1.dist-info/METADATA
flux0_core-0.1.0b1.dist-info/WHEEL
flux0_core-0.1.0b1.dist-info/RECORD
