Metadata-Version: 2.4
Name: flux0-core
Version: 0.1.0b1
Requires-Python: >=3.13
Requires-Dist: aiorwlock>=1.5.0
Requires-Dist: flux0-nanodb==0.1.0-beta.1
Requires-Dist: nanoid>=2.0.0
Requires-Dist: structlog>=25.1.0
